hostspy/__init__.py
hostspy-0.1.dist-info/LICENSE
hostspy-0.1.dist-info/METADATA
hostspy-0.1.dist-info/WHEEL
hostspy-0.1.dist-info/top_level.txt
hostspy-0.1.dist-info/RECORD
