Metadata-Version: 2.1
Name: hostspy
Version: 0.1
Summary: Wraper around 'ss' linux command
Home-page: https://github.com/shahbazk8194/hostspy
Author: Shahbaz Khan
Author-email: shahbazkhan8194@gmail.com
License: UNKNOWN
Platform: UNKNOWN
Classifier: Programming Language :: Python :: 3.5
Classifier: License :: OSI Approved :: MIT License
Classifier: Operating System :: POSIX :: Linux
